jaxtra/__init__.py
jaxtra/activations.py
jaxtra/data_loader.py
jaxtra/layers.py
jaxtra/models.py
jaxtra-0.0.2.dist-info/LICENSE
jaxtra-0.0.2.dist-info/METADATA
jaxtra-0.0.2.dist-info/WHEEL
jaxtra-0.0.2.dist-info/top_level.txt
jaxtra-0.0.2.dist-info/RECORD
